LICENSE
README.md
setup.py
PyGHee.egg-info/PKG-INFO
PyGHee.egg-info/SOURCES.txt
PyGHee.egg-info/dependency_links.txt
PyGHee.egg-info/requires.txt
PyGHee.egg-info/top_level.txt
pyghee/lib.py
pyghee/main.py
pyghee/utils.py
tests/test_events.py