Metadata-Version: 2.4
Name: PyGHee
Version: 0.1.0
Summary: PyGHee (pronounced as 'piggy') is the GitHub Event Executor, a Python library to facilitate creating a GitHub App implemented in Python to process [events from GitHub
Home-page: https://github.com/boegel/pyghee
Author: Kenneth Hoste
Author-email: kenneth.hoste@ugent.be
Project-URL: Bug Tracker, https://github.com/boegel/pyghee
Classifier: License :: OSI Approved :: GNU General Public License v2 (GPLv2)
Classifier: Operating System :: OS Independent
Classifier: Programming Language :: Python :: 3 :: Only
Requires-Python: >=3.6
License-File: LICENSE
Requires-Dist: Flask
Requires-Dist: PyGithub
Requires-Dist: waitress
Dynamic: author
Dynamic: author-email
Dynamic: classifier
Dynamic: description
Dynamic: description-content-type
Dynamic: home-page
Dynamic: license-file
Dynamic: project-url
Dynamic: requires-dist
Dynamic: requires-python
Dynamic: summary
